Pytorch_NLU-0.0.2.dist-info/DESCRIPTION.rst
Pytorch_NLU-0.0.2.dist-info/METADATA
Pytorch_NLU-0.0.2.dist-info/RECORD
Pytorch_NLU-0.0.2.dist-info/WHEEL
Pytorch_NLU-0.0.2.dist-info/metadata.json
Pytorch_NLU-0.0.2.dist-info/top_level.txt
pytorch_nlu/__init__.py
pytorch_nlu/version.py
pytorch_nlu/corpus/__init__.py
pytorch_nlu/corpus/sequence_labeling/__init__.py
pytorch_nlu/corpus/sequence_labeling/ner_china_people_daily_1998_conll/README.md
pytorch_nlu/corpus/sequence_labeling/ner_china_people_daily_1998_conll/dev.conll
pytorch_nlu/corpus/sequence_labeling/ner_china_people_daily_1998_conll/test.conll
pytorch_nlu/corpus/sequence_labeling/ner_china_people_daily_1998_conll/train.conll
pytorch_nlu/corpus/sequence_labeling/ner_china_people_daily_1998_span/README.md
pytorch_nlu/corpus/sequence_labeling/ner_china_people_daily_1998_span/dev.span
pytorch_nlu/corpus/sequence_labeling/ner_china_people_daily_1998_span/test.span
pytorch_nlu/corpus/sequence_labeling/ner_china_people_daily_1998_span/train.span
pytorch_nlu/corpus/text_classification/__init__.py
pytorch_nlu/corpus/text_classification/school/README.md
pytorch_nlu/corpus/text_classification/school/dev.json
pytorch_nlu/corpus/text_classification/school/test.json
pytorch_nlu/corpus/text_classification/school/train.json
pytorch_nlu/corpus/text_classification/tnews/README.md
pytorch_nlu/corpus/text_classification/tnews/dev.json
pytorch_nlu/corpus/text_classification/tnews/test.json
pytorch_nlu/corpus/text_classification/tnews/train.json
pytorch_nlu/output/__init__.py
pytorch_nlu/pytorch_sequencelabeling/__init__.py
pytorch_nlu/pytorch_sequencelabeling/slAdversarial.py
pytorch_nlu/pytorch_sequencelabeling/slConfig.py
pytorch_nlu/pytorch_sequencelabeling/slData.py
pytorch_nlu/pytorch_sequencelabeling/slGraph.py
pytorch_nlu/pytorch_sequencelabeling/slLayer.py
pytorch_nlu/pytorch_sequencelabeling/slOffice.py
pytorch_nlu/pytorch_sequencelabeling/slPredict.py
pytorch_nlu/pytorch_sequencelabeling/slRun.py
pytorch_nlu/pytorch_sequencelabeling/slTools.py
pytorch_nlu/pytorch_sequencelabeling/slTqdm.py
pytorch_nlu/pytorch_textclassification/__init__.py
pytorch_nlu/pytorch_textclassification/tcAdversarial.py
