Metadata-Version: 2.0
Name: Pytorch-NLU
Version: 0.0.2
Summary: Pytorch-NLU
Home-page: https://github.com/yongzhuo/Pytorch-NLU
Author: yongzhuo
Author-email: 1903865025@qq.com
License: Apache
Requires-Dist: numpy (>=1.18.1)
Requires-Dist: tensorboardX (>=2.4)
Requires-Dist: torch (>=1.9.0)
Requires-Dist: transformers (>=4.8.2)
